PyRigol_DS1000x/PyRigol_DS1000x.py
PyRigol_DS1000x/__init__.py
PyRigol_DS1000x-0.3.dist-info/LICENSE
PyRigol_DS1000x-0.3.dist-info/METADATA
PyRigol_DS1000x-0.3.dist-info/WHEEL
PyRigol_DS1000x-0.3.dist-info/top_level.txt
PyRigol_DS1000x-0.3.dist-info/RECORD
