Metadata-Version: 2.1
Name: PyRigol-DS1000x
Version: 0.3
Summary: module to easily contorl a Rigol DS1000x series scope and quickly build a measurement setup
Home-page: https://github.com/Minu-IU3IRR/PyRigol_DS1000x
Author: Manuel Minutello
License: MIT
License-File: LICENSE
Requires-Dist: pyvisa
